awsident/__init__.py
awsident/handlers.py
awsident/identity.py
awsident/main.py
awsident/storage.py
aws_identity_manager-0.0.3.dist-info/top_level.txt
aws_identity_manager-0.0.3.dist-info/entry_points.txt
aws_identity_manager-0.0.3.dist-info/METADATA
aws_identity_manager-0.0.3.dist-info/DESCRIPTION.rst
aws_identity_manager-0.0.3.dist-info/metadata.json
aws_identity_manager-0.0.3.dist-info/WHEEL
aws_identity_manager-0.0.3.dist-info/RECORD
