Metadata-Version: 2.0
Name: aws-identity-manager
Version: 0.0.3
Summary: Manage credentials for multiple AWS accounts
Home-page: https://github.com/nocarryr/AWS-Identity-Manager
Author: Matthew Reid
Author-email: matt@nomadic-recording.com
License: MIT
Keywords: aws
Platform: UNKNOWN
Classifier: Development Status :: 3 - Alpha
Classifier: Environment :: Console
Classifier: Intended Audience :: Developers
Classifier: Intended Audience :: Information Technology
Classifier: License :: OSI Approved :: MIT License
Classifier: Operating System :: OS Independent
Classifier: Programming Language :: Python
Classifier: Topic :: Utilities
Classifier: Programming Language :: Python :: 2
Classifier: Programming Language :: Python :: 2.7
Classifier: Programming Language :: Python :: 3
Classifier: Programming Language :: Python :: 3.4
Classifier: Programming Language :: Python :: 3.5
Requires-Dist: cmd2
